doc/conf.py
pytd/__init__.py
pytd/client.py
pytd/py.typed
pytd/query_engine.py
pytd/spark.py
pytd/table.py
pytd/writer.py
pytd/dbapi/__init__.py
pytd/dbapi/connection.py
pytd/dbapi/error.py
pytd/pandas_td/__init__.py
pytd/pandas_td/ipython.py
pytd-2.3.0.dist-info/licenses/LICENSE
pytd-2.3.0.dist-info/METADATA
pytd-2.3.0.dist-info/WHEEL
pytd-2.3.0.dist-info/top_level.txt
pytd-2.3.0.dist-info/RECORD
