Metadata-Version: 2.4
Name: pytd
Version: 2.3.0
Summary: Treasure Data Driver for Python
Author-email: Treasure Data <support@treasure-data.com>
Maintainer-email: Treasure Data <support@treasure-data.com>
License-Expression: Apache-2.0
Project-URL: Homepage, https://github.com/treasure-data/pytd
Project-URL: Repository, https://github.com/treasure-data/pytd
Keywords: database,treasure-data
Classifier: Development Status :: 5 - Production/Stable
Classifier: Intended Audience :: Developers
Classifier: Topic :: Database
Classifier: Programming Language :: Python
Classifier: Programming Language :: Python :: 3
Classifier: Programming Language :: Python :: 3.10
Classifier: Programming Language :: Python :: 3.11
Classifier: Programming Language :: Python :: 3.12
Classifier: Programming Language :: Python :: 3.13
Classifier: Programming Language :: Python :: 3.14
Requires-Python: >=3.10
License-File: LICENSE
Requires-Dist: urllib3>=1.21.1
Requires-Dist: trino>=0.334.0
Requires-Dist: pandas>=2.1.0
Requires-Dist: numpy>=1.25.2
Requires-Dist: td-client>=1.6.0
Requires-Dist: pytz>=2018.5
Requires-Dist: tqdm>=4.60.0
Provides-Extra: spark
Requires-Dist: td-pyspark>20.10.0; extra == "spark"
Requires-Dist: pyspark>=3.0.0; extra == "spark"
Requires-Dist: pyarrow>=10.0; extra == "spark"
Provides-Extra: test
Requires-Dist: pytest; extra == "test"
Provides-Extra: doc
Requires-Dist: sphinx>=2.2.0; extra == "doc"
Requires-Dist: sphinx_rtd_theme; extra == "doc"
Requires-Dist: numpydoc; extra == "doc"
Requires-Dist: ipython; extra == "doc"
Dynamic: license-file
